Shady/COPYING
Shady/CRS.py
Shady/CommandLineParsing.py
Shady/Console.py
Shady/Contrast.py
Shady/DPI.py
Shady/Dependencies.py
Shady/DependencyManagement.py
Shady/Documentation.py
Shady/Dynamics.py
Shady/Events.py
Shady/GL.py
Shady/KeystrokesWithoutWindow.py
Shady/Linearization.py
Shady/Logging.py
Shady/MASTER_META
Shady/Meta.py
Shady/PropertyManagement.py
Shady/PyEngine.py
Shady/PygameWindowing.py
Shady/PygletWindowing.py
Shady/Rendering.py
Shady/ShaDyLibWindowing.py
Shady/Testing.py
Shady/Text.py
Shady/Timing.py
Shady/Utilities.py
Shady/Video.py
Shady/__init__.py
Shady/__main__.py
Shady/VPixx/__init__.py
Shady/VPixx/bin/LICENSE-libdpx.txt
Shady/VPixx/bin/LICENSE-libusb-win32.txt
Shady/VPixx/bin/LICENSE-libusb.txt
Shady/VPixx/bin/Darwin-64bit/dpxmode
Shady/VPixx/bin/Darwin-arm64/dpxmode
Shady/VPixx/bin/Windows-32bit/dpxmode.exe
Shady/VPixx/bin/Windows-32bit/libusb0.dll
Shady/VPixx/bin/Windows-64bit/dpxmode.exe
Shady/VPixx/bin/Windows-64bit/libusb0.dll
Shady/accel/ShaDyLib.h
Shady/accel/ShaDyLib.py
Shady/accel/__init__.py
Shady/accel/libShady-Darwin-64bit.dylib
Shady/accel/libShady-Darwin-arm64.dylib
Shady/accel/libShady-Linux-64bit.so
Shady/accel/libShady-Windows-32bit.dll
Shady/accel/libShady-Windows-64bit.dll
Shady/examples/BitStealingLUT_maxDACDeparture=2_Cmax=3.0_nbits=16_gamma=sRGB.npz
Shady/examples/BitStealingLUT_maxDACDeparture=2_Cmax=3.0_nbits=16_gamma=sRGB.png
Shady/examples/after-sarcone.py
Shady/examples/animated-textures.py
Shady/examples/artifacts.py
Shady/examples/capture-video.py
Shady/examples/color-transformation.py
Shady/examples/custom-functions.py
Shady/examples/dithering.py
Shady/examples/dots1.py
Shady/examples/dots2.py
Shady/examples/dots3.py
Shady/examples/dots4.py
Shady/examples/dynamic-range.py
Shady/examples/dynamics1.py
Shady/examples/dynamics2.py
Shady/examples/events.py
Shady/examples/fancy-hardware.py
Shady/examples/foreign-stimulus.py
Shady/examples/image-scaling.py
Shady/examples/interactive-gamma.py
Shady/examples/noise.py
shady-1.17.0.dist-info/licenses/COPYING
shady-1.17.0.dist-info/METADATA
shady-1.17.0.dist-info/WHEEL
shady-1.17.0.dist-info/top_level.txt
shady-1.17.0.dist-info/RECORD
