Metadata-Version: 2.4
Name: Shady
Version: 1.17.0
Summary: An engine for real-time manipulation of visual stimuli for neuroscience, implemented via GPU shaders
Home-page: https://shady.readthedocs.io
Author: Jeremy Hill, Scott Mooney
Author-email: jezhill@gmail.com
License: GPL v3+
Requires-Python: >=2.7, !=3.0.*, !=3.1.*, !=3.2.*, <4
License-File: COPYING
Requires-Dist: numpy
Requires-Dist: pillow
Requires-Dist: matplotlib
Requires-Dist: ipython
Provides-Extra: textures
Requires-Dist: numpy; extra == "textures"
Provides-Extra: images
Requires-Dist: numpy; extra == "images"
Requires-Dist: pillow; extra == "images"
Provides-Extra: fonts
Requires-Dist: numpy; extra == "fonts"
Requires-Dist: pillow; extra == "fonts"
Requires-Dist: matplotlib; extra == "fonts"
Provides-Extra: shell
Requires-Dist: ipython; extra == "shell"
Provides-Extra: video
Requires-Dist: numpy; extra == "video"
Requires-Dist: opencv-python; extra == "video"
Provides-Extra: pure
Requires-Dist: pyglet; extra == "pure"
Dynamic: author
Dynamic: author-email
Dynamic: description
Dynamic: description-content-type
Dynamic: home-page
Dynamic: license
Dynamic: license-file
Dynamic: provides-extra
Dynamic: requires-dist
Dynamic: requires-python
Dynamic: summary
